{
  "version": "1.0.0",
  "library": "@aily-project/lib-tcs34725",
  "displayName": "TCS34725 颜色传感器",
  "type": "library",
  "models": [
    {
      "id": "tcs34725",
      "name": "TCS34725",
      "description": "I2C RGB颜色传感器，内置红外遮挡滤光片和LED，直接输出RGBC四通道光照值。",
      "defaultVariant": "module",
      "variants": [
        {
          "id": "module",
          "name": "标准模块",
          "fullId": "lib-tcs34725:tcs34725:module",
          "pinmapFile": "pinmaps/tcs34725_module.json",
          "protocol": "i2c",
          "status": "available",
          "isDefault": true,
          "previewPins": ["VCC", "GND", "SDA", "SCL"]
        }
      ]
    }
  ]
}
